README.rst
setup.py
wishbone_input_httpserver/__init__.py
wishbone_input_httpserver/app.py
wishbone_input_httpserver/httpserver.py
wishbone_input_httpserver.egg-info/PKG-INFO
wishbone_input_httpserver.egg-info/SOURCES.txt
wishbone_input_httpserver.egg-info/dependency_links.txt
wishbone_input_httpserver.egg-info/entry_points.txt
wishbone_input_httpserver.egg-info/namespace_packages.txt
wishbone_input_httpserver.egg-info/not-zip-safe
wishbone_input_httpserver.egg-info/requires.txt
wishbone_input_httpserver.egg-info/top_level.txt
wishbone_input_httpserver/middleware/__init__.py
wishbone_input_httpserver/middleware/authorise.py
wishbone_input_httpserver/middleware/basic_authentication.py
wishbone_input_httpserver/middleware/data_extractor.py
wishbone_input_httpserver/middleware/derivequeue.py
wishbone_input_httpserver/middleware/generatemetadata.py
wishbone_input_httpserver/middleware/token_authentication.py