Metadata-Version: 1.1
Name: wishbone-input-httpserver
Version: 3.0.7
Summary: A Wishbone input module to receive events over HTTP.
Home-page: https://github.com/smetj/wishbone-input-httpserver
Author: Jelle Smet
Author-email: development@smetj.net
License: UNKNOWN
Download-URL: https://github.com/smetj/wishbone-input-httpserver/tarball/master
Platform: Linux
Classifier: Development Status :: 5 - Production/Stable
Classifier: License :: OSI Approved :: GNU General Public License v3 or later (GPLv3+)
Classifier: Programming Language :: Python
Classifier: Programming Language :: Python :: 2.7
Classifier: Programming Language :: Python :: Implementation :: PyPy
Classifier: Intended Audience :: Developers
Classifier: Intended Audience :: System Administrators
